{
    "error": null,
    "dataset": "3779886",
    "dataset_md5": "01f7e8c5083d66e47313f437fa78fbd9",
    "hostname": "no_host",
    "status": "SUCCESS",
    "parameters": {
        "mozilla_method": "Mozilla",
        "cpnp_method": "PELT",
        "cpnp_test.stat": "empirical_distribution",
        "cpnp_minseglen": 1,
        "cpnp_nquantiles": 10,
        "cpnp_penalty": "MBIC"
    },
    "args": {
        "mozilla_method": "Mozilla",
        "cpnp_nquantiles": 10,
        "cpnp_penalty": "MBIC"
    },
    "result": {
        "cplocations": [
            221,
            258,
            270,
            362,
            467,
            499,
            534,
            547,
            582,
            601,
            981,
            1004,
            1064,
            1162,
            1181,
            1239,
            1255,
            1333,
            1380,
            1494,
            1497,
            1559,
            1629,
            1646,
            1659,
            1828,
            1933,
            1953,
            2101,
            2130,
            2150,
            2216,
            2303,
            2345,
            2415,
            2465,
            2488,
            2556,
            2568,
            2582,
            2605,
            2621,
            2622,
            2673,
            2674,
            2976,
            3340,
            3380,
            3473,
            3540,
            3552
        ],
        "runtime": 0.08328223
    }
}