{
    "error": null,
    "dataset": "4405777",
    "dataset_md5": "446f06be70f61784da815016c371bf6e",
    "hostname": "d30854552e89",
    "status": "SUCCESS",
    "parameters": {
        "bocpd_missPts": "none",
        "bocpd_cpthreshold": 0.5,
        "bocpd_truncRlim": 0.0001,
        "bocpd_minRlength": 1,
        "bocpd_maxRlength": 10000,
        "bocpd_minsep": 1,
        "bocpd_maxsep": 10000,
        "bocpd_multivariate": false,
        "bocpd_lambda": 50,
        "bocpd_prior_a": 0.01,
        "bocpd_prior_b": 1,
        "bocpd_prior_k": 100,
        "binseg_Q": 1334.5,
        "binseg_pen.value": 0,
        "binseg_func": "meanvar",
        "binseg_max_cp": "max",
        "binseg_method": "BinSeg",
        "binseg_penalty": "None",
        "binseg_test_statistic": "Normal"
    },
    "args": {
        "bocpd_lambda": 50,
        "bocpd_prior_a": 0.01,
        "bocpd_prior_b": 1,
        "bocpd_prior_k": 100,
        "binseg_func": "meanvar",
        "binseg_max_cp": "max",
        "binseg_method": "BinSeg",
        "binseg_penalty": "None",
        "binseg_test_statistic": "Normal"
    },
    "result": {
        "cplocations": [
            3,
            6,
            8,
            11,
            13,
            17,
            20,
            22,
            25,
            27,
            31,
            33,
            35,
            37,
            39,
            42,
            46,
            48,
            52,
            54,
            56,
            58,
            61,
            63,
            66,
            68,
            72,
            74,
            77,
            80,
            83,
            86,
            88,
            92,
            96,
            100,
            103,
            105,
            107,
            111,
            114,
            118,
            121,
            124,
            127,
            129,
            133,
            136,
            140,
            144,
            148,
            151,
            153,
            156,
            159,
            161,
            163,
            166,
            168,
            171,
            173,
            176,
            179,
            182,
            184,
            186,
            189,
            192,
            195,
            197,
            199,
            201,
            203,
            206,
            208,
            212,
            216,
            219,
            221,
            224,
            227,
            230,
            234,
            237,
            239,
            242,
            244,
            248,
            251,
            253,
            256,
            258,
            261,
            263,
            265,
            269,
            271,
            274,
            278,
            281,
            283,
            286,
            290,
            293,
            295,
            297,
            300,
            303,
            305,
            308,
            311,
            314,
            318,
            320,
            324,
            326,
            329,
            333,
            335,
            337,
            340,
            343,
            345,
            347,
            349,
            352,
            354,
            357,
            359,
            362,
            365,
            367,
            369,
            373,
            375,
            378,
            381,
            385,
            387,
            391,
            394,
            397,
            399,
            402,
            404,
            407,
            411,
            414,
            416,
            419,
            422,
            424,
            427,
            431,
            433,
            436,
            439,
            441,
            443,
            446,
            448,
            452,
            456,
            459,
            461,
            463,
            465,
            468,
            470,
            472,
            474,
            477,
            481,
            483,
            485,
            487,
            491,
            493,
            497,
            499,
            501,
            504,
            507,
            509,
            513,
            517,
            520,
            522,
            526,
            530,
            533,
            536,
            538,
            541,
            543,
            546,
            549,
            551,
            553,
            557,
            560,
            563,
            565,
            568,
            571,
            574,
            576,
            579,
            583,
            586,
            589,
            591,
            594,
            597,
            600,
            602,
            605,
            609,
            612,
            614,
            617,
            619,
            623,
            626,
            628,
            631,
            634,
            637,
            640,
            644,
            646,
            649,
            652,
            654,
            657,
            660,
            662,
            665,
            667,
            670,
            673,
            675,
            677,
            680,
            683,
            687,
            691,
            695,
            699,
            702,
            705,
            708,
            711,
            714,
            716,
            719,
            722,
            725,
            727,
            730,
            732,
            735,
            737,
            739,
            741,
            744,
            746,
            750,
            753,
            755,
            757,
            759,
            761,
            764,
            766,
            770,
            772,
            775,
            779,
            782,
            785,
            787,
            789,
            792,
            794,
            798,
            801,
            804,
            808,
            811,
            813,
            817,
            821,
            823,
            827,
            830,
            833,
            835,
            838,
            840,
            843,
            845,
            847,
            851,
            853,
            856,
            860,
            864,
            867,
            870,
            872,
            874,
            877,
            880,
            883,
            887,
            889,
            892,
            896,
            898,
            901,
            903,
            907,
            909,
            910,
            912,
            914,
            917,
            921,
            924,
            927,
            929,
            932,
            935,
            938,
            940,
            942,
            945,
            947,
            950,
            953,
            957,
            960,
            964,
            967,
            970,
            972,
            976,
            979,
            982,
            984,
            987,
            990,
            992,
            996,
            998,
            1001,
            1004,
            1007,
            1009,
            1011,
            1013,
            1016,
            1019,
            1021,
            1023,
            1025,
            1027,
            1029,
            1033,
            1035,
            1038,
            1040,
            1042,
            1045,
            1049,
            1051,
            1055,
            1059,
            1061,
            1065,
            1069,
            1071,
            1073,
            1076,
            1079,
            1081,
            1085,
            1088,
            1091,
            1093,
            1095,
            1099,
            1102,
            1105,
            1109,
            1112,
            1114,
            1117,
            1120,
            1122,
            1125,
            1128,
            1131,
            1133,
            1135,
            1138,
            1140,
            1142,
            1144,
            1148,
            1151,
            1154,
            1156,
            1159,
            1162,
            1164,
            1166,
            1169,
            1172,
            1174,
            1177,
            1179,
            1181,
            1183,
            1187,
            1190,
            1194,
            1197,
            1200,
            1202,
            1205,
            1208,
            1211,
            1214,
            1216,
            1219,
            1222,
            1225,
            1228,
            1230,
            1233,
            1235,
            1237,
            1241,
            1244,
            1247,
            1249,
            1253,
            1255,
            1258,
            1262,
            1265,
            1267,
            1271,
            1274,
            1277,
            1279,
            1281,
            1284,
            1287,
            1290,
            1293,
            1295,
            1297,
            1301,
            1304,
            1308,
            1311,
            1314,
            1317,
            1320,
            1322,
            1325,
            1327,
            1331,
            1334,
            1338,
            1340,
            1343,
            1345,
            1349,
            1352,
            1354,
            1357,
            1360,
            1364,
            1366,
            1368,
            1371,
            1374,
            1376,
            1378,
            1381,
            1383,
            1386,
            1389,
            1391,
            1395,
            1398,
            1401,
            1405,
            1408,
            1411,
            1415,
            1417,
            1419,
            1422,
            1424,
            1427,
            1431,
            1434,
            1437,
            1439,
            1442,
            1445,
            1447,
            1449,
            1451,
            1455,
            1457,
            1461,
            1464,
            1468,
            1471,
            1473,
            1476,
            1479,
            1482,
            1484,
            1487,
            1489,
            1492,
            1494,
            1497,
            1499,
            1502,
            1504,
            1507,
            1509,
            1513,
            1516,
            1519,
            1522,
            1524,
            1527,
            1530,
            1533,
            1537,
            1539,
            1543,
            1545,
            1548,
            1550,
            1554,
            1557,
            1559,
            1562,
            1565,
            1569,
            1572,
            1574,
            1576,
            1578,
            1580,
            1584,
            1587,
            1590,
            1592,
            1594,
            1598,
            1601,
            1604,
            1606,
            1608,
            1611,
            1613,
            1615,
            1618,
            1622,
            1625,
            1628,
            1630,
            1633,
            1635,
            1638,
            1642,
            1646,
            1649,
            1652,
            1655,
            1658,
            1662,
            1666,
            1669,
            1672,
            1674,
            1678,
            1680,
            1682,
            1685,
            1687,
            1690,
            1692,
            1696,
            1699,
            1703,
            1705,
            1707,
            1709,
            1711,
            1713,
            1716,
            1719,
            1722,
            1725,
            1727,
            1729,
            1733,
            1735,
            1739,
            1742,
            1745,
            1748,
            1752,
            1754,
            1758,
            1762,
            1765,
            1768,
            1770,
            1773,
            1777,
            1779,
            1782,
            1784,
            1786,
            1789,
            1791,
            1793,
            1796,
            1799,
            1802,
            1805,
            1808,
            1810,
            1813,
            1815,
            1818,
            1821,
            1824,
            1827,
            1829,
            1831,
            1834,
            1836,
            1838,
            1841,
            1843,
            1845,
            1848,
            1852,
            1855,
            1857,
            1860,
            1862,
            1865,
            1867,
            1870,
            1872,
            1874,
            1876,
            1880,
            1882,
            1885,
            1888,
            1891,
            1894,
            1897,
            1900,
            1902,
            1904,
            1907,
            1909,
            1911,
            1915,
            1917,
            1920,
            1924,
            1926,
            1928,
            1930,
            1933,
            1936,
            1939,
            1942,
            1944,
            1947,
            1950,
            1953,
            1956,
            1958,
            1961,
            1963,
            1965,
            1967,
            1971,
            1975,
            1979,
            1982,
            1985,
            1989,
            1992,
            1995,
            1999,
            2003,
            2006,
            2009,
            2011,
            2015,
            2017,
            2019,
            2021,
            2024,
            2027,
            2029,
            2031,
            2035,
            2038,
            2042,
            2045,
            2048,
            2051,
            2053,
            2055,
            2058,
            2062,
            2065,
            2067,
            2069,
            2073,
            2075,
            2078,
            2080,
            2082,
            2085,
            2087,
            2089,
            2091,
            2093,
            2095,
            2099,
            2102,
            2104,
            2107,
            2110,
            2112,
            2115,
            2118,
            2122,
            2124,
            2126,
            2128,
            2131,
            2133,
            2136,
            2139,
            2142,
            2146,
            2149,
            2151,
            2153,
            2156,
            2159,
            2161,
            2164,
            2166,
            2169,
            2172,
            2175,
            2177,
            2180,
            2184,
            2186,
            2189,
            2193,
            2196,
            2200,
            2202,
            2204,
            2208,
            2212,
            2215,
            2218,
            2221,
            2223,
            2225,
            2228,
            2231,
            2235,
            2239,
            2242,
            2246,
            2249,
            2251,
            2253,
            2255,
            2257,
            2261,
            2265,
            2268,
            2270,
            2273,
            2277,
            2281,
            2283,
            2285,
            2287,
            2290,
            2292,
            2294,
            2297,
            2299,
            2302,
            2306,
            2309,
            2311,
            2315,
            2318,
            2321,
            2323,
            2326,
            2329,
            2332,
            2335,
            2339,
            2342,
            2345,
            2347,
            2351,
            2353,
            2357,
            2359,
            2361,
            2363,
            2366,
            2368,
            2370,
            2373,
            2375,
            2378,
            2380,
            2382,
            2385,
            2388,
            2390,
            2392,
            2395,
            2397,
            2400,
            2404,
            2408,
            2411,
            2414,
            2417,
            2420,
            2422,
            2425,
            2428,
            2430,
            2434,
            2438,
            2441,
            2443,
            2446,
            2449,
            2453,
            2456,
            2458,
            2461,
            2463,
            2467,
            2470,
            2474,
            2476,
            2479,
            2483,
            2485,
            2487,
            2490,
            2492,
            2494,
            2498,
            2500,
            2503,
            2505,
            2507,
            2510,
            2513,
            2515,
            2519,
            2522,
            2525,
            2527,
            2529,
            2532,
            2534,
            2538,
            2542,
            2544,
            2545,
            2547,
            2550,
            2553,
            2555,
            2558,
            2560,
            2563,
            2566,
            2569,
            2572,
            2576,
            2579,
            2583,
            2586,
            2590,
            2593,
            2595,
            2598,
            2602,
            2606,
            2608,
            2612,
            2616,
            2618,
            2621,
            2623,
            2626,
            2629,
            2632,
            2636,
            2639,
            2643,
            2645,
            2647,
            2649,
            2652,
            2655,
            2657,
            2659,
            2662,
            2664
        ],
        "runtime": 1.3717445
    }
}