{
    "error": null,
    "dataset": "4722823",
    "dataset_md5": "75f0ab40169a00087f48814ed3401c4e",
    "hostname": "d30854552e89",
    "status": "SUCCESS",
    "parameters": {
        "binseg_Q": 1144.5,
        "binseg_pen.value": 0,
        "binseg_func": "meanvar",
        "binseg_max_cp": "max",
        "binseg_method": "BinSeg",
        "binseg_penalty": "SIC",
        "binseg_test_statistic": "Normal"
    },
    "args": {
        "mongodb_permutations": 50,
        "mongodb_pvalue": 0.05,
        "binseg_func": "meanvar",
        "binseg_max_cp": "max",
        "binseg_method": "BinSeg",
        "binseg_penalty": "SIC",
        "binseg_test_statistic": "Normal"
    },
    "result": {
        "cplocations": [
            74,
            93,
            220,
            234,
            296,
            304,
            378,
            473,
            499,
            517,
            553,
            613,
            682,
            689,
            754,
            825,
            832,
            857,
            888,
            902,
            946,
            1155,
            1159,
            1177,
            1206,
            1308,
            1440,
            1485,
            1548,
            1583,
            1600,
            1725,
            1935,
            2002,
            2020,
            2190,
            2211
        ],
        "runtime": 9.377972121148682
    }
}