{
	"error" : null,
	"command" : "/usr/lib/R/bin/exec/R --slave --no-restore --no-save --slave --file=/TCPDBench/execs/R/cpdbench_changepointnp.R --args -i /TCPDBench/datasets/3870269.json -p SIC -q 40",
	"script" : "/TCPDBench/execs/R/cpdbench_changepointnp.R",
	"script_md5" : "43ed9dac8cb9570e29df4eeae78efd13",
	"hostname" : "56cdd2de670c",
	"dataset" : "3870269",
	"dataset_md5" : "1f01e51c69248f592665f2bf1b74804e",
	"status" : "SUCCESS",
	"parameters" : {
		"method" : "PELT",
		"test.stat" : "empirical_distribution",
		"minseglen" : 1,
		"nquantiles" : 40,
		"penalty" : "SIC"
	},
	"result" : {
		"cplocations" : [
			14,
			101,
			320,
			455,
			538,
			903,
			940,
			959,
			1243,
			1302,
			1321,
			1366,
			1489,
			1683,
			1712,
			1805,
			1836,
			1848,
			1867,
			1955,
			1991,
			2011,
			2057,
			2191,
			2227,
			2269,
			2313,
			2398,
			2417,
			2426,
			2531,
			2615,
			2698,
			2740,
			2761,
			2783,
			3001
		],
		"runtime" : 0.1830246
	},
	"args" : {
		"nquantiles" : 40,
		"penalty" : "SIC"
	}
} 
