{
    "error": null,
    "dataset": "4405667",
    "dataset_md5": "49ce6bfee1c435762a3f7e67edc3d7e2",
    "hostname": "no_host",
    "status": "SUCCESS",
    "parameters": {
        "mozilla_method": "Mozilla",
        "wbs_M": 5000,
        "wbs_rand.intervals": true,
        "wbs_Kmax": 50,
        "wbs_integrated": true,
        "wbs_penalty": "SSIC"
    },
    "args": {
        "mozilla_method": "Mozilla",
        "wbs_Kmax": "default",
        "wbs_integrated": "true",
        "wbs_penalty": "SSIC"
    },
    "result": {
        "cplocations": [
            16,
            133,
            135,
            136,
            137,
            138,
            140,
            433,
            434,
            564,
            567,
            875,
            884,
            910,
            955,
            1031,
            1033,
            1036,
            1140,
            1141,
            1143,
            1144,
            1185,
            1192,
            1216,
            1234,
            1271,
            1297,
            1376,
            1597,
            1624,
            1648,
            1660,
            1737,
            1762,
            1784,
            1785,
            1840,
            1891,
            1898,
            1993,
            1994,
            2020,
            2170,
            2189,
            2232,
            2249,
            2250,
            2267,
            2295,
            2456,
            2500,
            2501
        ],
        "runtime": 0.1151686
    }
}