{
    "error": null,
    "dataset": "3777906",
    "dataset_md5": "db0bfd70d5475ecbd65f358513f4d7d8",
    "hostname": "d30854552e89",
    "status": "SUCCESS",
    "parameters": {
        "binseg_Q": 1429,
        "binseg_pen.value": 0,
        "binseg_func": "var",
        "binseg_max_cp": "max",
        "binseg_method": "BinSeg",
        "binseg_penalty": "Hannan-Quinn",
        "binseg_test_statistic": "Normal"
    },
    "args": {
        "mongodb_permutations": 10,
        "mongodb_pvalue": 0.01,
        "binseg_func": "var",
        "binseg_max_cp": "max",
        "binseg_method": "BinSeg",
        "binseg_penalty": "Hannan-Quinn",
        "binseg_test_statistic": "Normal"
    },
    "result": {
        "cplocations": [
            96,
            104,
            267,
            270,
            283,
            322,
            351,
            435,
            438,
            500,
            506,
            546,
            581,
            586,
            633,
            635,
            889,
            1051,
            1288,
            1298,
            1405,
            1433,
            1442,
            1444,
            1534,
            1728,
            1800,
            2249,
            2327,
            2493,
            2521
        ],
        "runtime": 2.5602064304107666
    }
}