{
	"args": {
		"permutations": 150,
		"pvalue": 0.01
	},
	"command": "/TCPDBench/execs/python/cpdbench_mongodb.py -i /TCPDBench/datasets/4408340.json --pvalue 0.01 --permutations 150",
	"dataset": "4408340",
	"dataset_md5": "f298050e5db208653a3267731de2bcb7",
	"error": null,
	"hostname": "5e18e3e0ef3f",
	"parameters": {},
	"result": {
		"cplocations": [
			97,
			436,
			151,
			381,
			646,
			464
		],
		"runtime": 1.3399405479431152
	},
	"script": "/TCPDBench/execs/python/cpdbench_mongodb.py",
	"script_md5": "184cb980dcf56d53396e0141d684c9ef",
	"status": "SUCCESS"
}
