{
    "error": null,
    "dataset": "4168126",
    "dataset_md5": "28963c9147ce0d1935d699552cb0cccb",
    "hostname": "d30854552e89",
    "status": "SUCCESS",
    "parameters": {
        "bocpd_missPts": "none",
        "bocpd_cpthreshold": 0.5,
        "bocpd_truncRlim": 0.0001,
        "bocpd_minRlength": 1,
        "bocpd_maxRlength": 10000,
        "bocpd_minsep": 1,
        "bocpd_maxsep": 10000,
        "bocpd_multivariate": false,
        "bocpd_lambda": 100,
        "bocpd_prior_a": 1,
        "bocpd_prior_b": 100,
        "bocpd_prior_k": 100,
        "binseg_Q": 404.5,
        "binseg_pen.value": 0,
        "binseg_func": "var",
        "binseg_max_cp": "max",
        "binseg_method": "BinSeg",
        "binseg_penalty": "BIC",
        "binseg_test_statistic": "Normal"
    },
    "args": {
        "bocpd_lambda": 100,
        "bocpd_prior_a": 1,
        "bocpd_prior_b": 100,
        "bocpd_prior_k": 100,
        "binseg_func": "var",
        "binseg_max_cp": "max",
        "binseg_method": "BinSeg",
        "binseg_penalty": "BIC",
        "binseg_test_statistic": "Normal"
    },
    "result": {
        "cplocations": [],
        "runtime": 0.40758295
    }
}