{
	"args": {
		"kernel": "linear",
		"maxcp": 2,
		"minsize": 5.0
	},
	"command": "/TCPDBench/execs/python/cpdbench_kcpa.py -i /TCPDBench/datasets/3777972.json --maxcp 2 --minsize 5 --kernel linear",
	"dataset": "3777972",
	"dataset_md5": "efdd512053d4f4ec293713146432d5e7",
	"error": null,
	"hostname": "b2b3534b7c26",
	"parameters": {
		"input": "/TCPDBench/datasets/3777972.json",
		"kernel": "linear",
		"maxcp": 2,
		"minsize": 5.0,
		"output": null
	},
	"result": {
		"cplocations": [
			1398,
			2474,
			2622
		],
		"runtime": 0.05168652534484863
	},
	"script": "/TCPDBench/execs/python/cpdbench_kcpa.py",
	"script_md5": "16b44f4bdbc91472e1d735dda466a919",
	"status": "SUCCESS"
}
