{
    "error": null,
    "dataset": "3778074",
    "dataset_md5": "0e8e049e2d013baab38cc0e5da48edcd",
    "hostname": "d30854552e89",
    "status": "SUCCESS",
    "parameters": {
        "bocpd_missPts": "none",
        "bocpd_cpthreshold": 0.5,
        "bocpd_truncRlim": 0.0001,
        "bocpd_minRlength": 1,
        "bocpd_maxRlength": 10000,
        "bocpd_minsep": 1,
        "bocpd_maxsep": 10000,
        "bocpd_multivariate": false,
        "bocpd_lambda": 100,
        "bocpd_prior_a": 100,
        "bocpd_prior_b": 0.01,
        "bocpd_prior_k": 1
    },
    "args": {
        "mongodb_permutations": 10,
        "mongodb_pvalue": 0.05,
        "bocpd_lambda": 100,
        "bocpd_prior_a": 100,
        "bocpd_prior_b": 0.01,
        "bocpd_prior_k": 1
    },
    "result": {
        "cplocations": [
            22,
            104,
            120,
            171,
            255,
            272,
            279,
            389,
            508,
            672,
            725,
            993,
            1152,
            1203,
            1270,
            1315,
            1347,
            1395,
            1437,
            1512,
            1601,
            1661,
            1743,
            2024,
            2254,
            2308,
            2369,
            2601,
            3317,
            3495
        ],
        "runtime": 9.562915947494506
    }
}