{
	"error" : null,
	"command" : "/usr/lib/R/bin/exec/R --slave --no-restore --no-save --slave --file=/TCPDBench/execs/R/cpdbench_changepointnp.R --args -i /TCPDBench/datasets/3777937.json -p Hannan-Quinn -q 30",
	"script" : "/TCPDBench/execs/R/cpdbench_changepointnp.R",
	"script_md5" : "43ed9dac8cb9570e29df4eeae78efd13",
	"hostname" : "7233945ba110",
	"dataset" : "3777937",
	"dataset_md5" : "441c2cbca47809b5d8b50f23101aa430",
	"status" : "SUCCESS",
	"parameters" : {
		"method" : "PELT",
		"test.stat" : "empirical_distribution",
		"minseglen" : 1,
		"nquantiles" : 30,
		"penalty" : "Hannan-Quinn"
	},
	"result" : {
		"cplocations" : [
			12,
			27,
			47,
			98,
			116,
			125,
			135,
			140,
			154,
			179,
			195,
			237,
			306,
			314,
			325,
			352,
			409,
			415,
			430,
			441,
			449,
			501,
			518,
			525,
			553,
			574,
			607,
			648,
			673,
			708,
			776,
			825,
			845,
			880,
			886,
			909,
			914,
			924,
			930,
			942,
			957,
			962,
			976,
			994,
			1000,
			1008,
			1031,
			1043,
			1108,
			1127,
			1134,
			1142,
			1152,
			1180,
			1192,
			1200,
			1210,
			1220,
			1234,
			1247,
			1255,
			1269,
			1286,
			1330,
			1364,
			1398,
			1422,
			1434,
			1442,
			1515,
			1522,
			1529,
			1548,
			1579,
			1590,
			1670,
			1689,
			1702,
			1711,
			1730,
			1738,
			1764,
			1782,
			1788,
			1828,
			1839,
			1856,
			1864,
			1872,
			1892,
			1903,
			1915,
			1922,
			1933,
			1966,
			1971,
			1978,
			1984,
			1987,
			2047,
			2051,
			2085,
			2089,
			2132,
			2193,
			2204,
			2219,
			2236,
			2245,
			2270,
			2284,
			2293,
			2299,
			2329,
			2335,
			2356,
			2404,
			2406,
			2411,
			2435,
			2443,
			2460,
			2541,
			2564,
			2578,
			2584,
			2601,
			2607,
			2619,
			2627,
			2646,
			2664,
			2672,
			2693,
			2708,
			2713,
			2728,
			2745,
			2765
		],
		"runtime" : 0.03907132
	},
	"args" : {
		"nquantiles" : 30,
		"penalty" : "Hannan-Quinn"
	}
} 
