{
	"error" : null,
	"command" : "/usr/lib/R/bin/exec/R --slave --no-restore --no-save --slave --file=/TCPDBench/execs/R/cpdbench_changepoint.R --args -i /TCPDBench/datasets/4405662.json -p SIC -f var -t Normal -m BinSeg -Q max",
	"script" : "/TCPDBench/execs/R/cpdbench_changepoint.R",
	"script_md5" : "c5a9eb6b79b918fc674b55b669629f44",
	"hostname" : "d30854552e89",
	"dataset" : "4405662",
	"dataset_md5" : "7a211ab7f972b4d2182175f403aa810c",
	"status" : "SUCCESS",
	"parameters" : {
		"Q" : 1318,
		"pen.value" : 0,
		"func" : "var",
		"max_cp" : "max",
		"method" : "BinSeg",
		"penalty" : "SIC",
		"test_statistic" : "Normal"
	},
	"result" : {
		"cplocations" : [
			133,
			140,
			433,
			435,
			874,
			955,
			1000,
			1002,
			1031,
			1037,
			1140,
			1144,
			1169,
			1194,
			1234,
			1260,
			1367,
			1599,
			1635,
			1662,
			1737,
			1762,
			1783,
			1785,
			1840,
			1891,
			1993,
			1997,
			2021,
			2169,
			2180,
			2233,
			2299,
			2457
		],
		"runtime" : 0.2864654
	},
	"args" : {
		"func" : "var",
		"max_cp" : "max",
		"method" : "BinSeg",
		"penalty" : "SIC",
		"test_statistic" : "Normal"
	}
} 
