{
	"error" : null,
	"command" : "/usr/lib/R/bin/exec/R --slave --no-restore --no-save --slave --file=/TCPDBench/execs/R/cpdbench_ocp.R --args -i /TCPDBench/datasets/3870270.json -l 50 --prior-a 0.01 --prior-b 0.01 --prior-k 0.01",
	"script" : "/TCPDBench/execs/R/cpdbench_ocp.R",
	"script_md5" : "c8f652930f61de1aa9c9b558f3010139",
	"hostname" : "56cdd2de670c",
	"dataset" : "3870270",
	"dataset_md5" : "cb65c8fb55ae9c70034af929c8a44bf8",
	"status" : "SUCCESS",
	"parameters" : {
		"missPts" : "none",
		"cpthreshold" : 0.5,
		"truncRlim" : 0.0001,
		"minRlength" : 1,
		"maxRlength" : 10000,
		"minsep" : 1,
		"maxsep" : 10000,
		"multivariate" : false,
		"lambda" : 50,
		"prior_a" : 0.01,
		"prior_b" : 0.01,
		"prior_k" : 0.01
	},
	"result" : {
		"cplocations" : [
			6,
			13,
			24,
			109,
			155,
			162,
			275,
			455,
			458,
			903,
			959,
			1019,
			1048,
			1054,
			1160,
			1188,
			1209,
			1243,
			1278,
			1284,
			1302,
			1321,
			1358,
			1489,
			1574,
			1610,
			1620,
			1682,
			1712,
			1805,
			1835,
			1848,
			1867,
			1955,
			2041,
			2051,
			2111,
			2204,
			2227,
			2270,
			2398,
			2426,
			2531,
			2616,
			2699,
			2736,
			2761,
			2795,
			3001
		],
		"runtime" : 1.067515
	},
	"args" : {
		"lambda" : 50,
		"prior_a" : 0.01,
		"prior_b" : 0.01,
		"prior_k" : 0.01
	}
} 
