{
    "error": null,
    "dataset": "4405667",
    "dataset_md5": "49ce6bfee1c435762a3f7e67edc3d7e2",
    "hostname": "d30854552e89",
    "status": "SUCCESS",
    "parameters": {
        "bocpd_missPts": "none",
        "bocpd_cpthreshold": 0.5,
        "bocpd_truncRlim": 0.0001,
        "bocpd_minRlength": 1,
        "bocpd_maxRlength": 10000,
        "bocpd_minsep": 1,
        "bocpd_maxsep": 10000,
        "bocpd_multivariate": false,
        "bocpd_lambda": 100,
        "bocpd_prior_a": 100,
        "bocpd_prior_b": 100,
        "bocpd_prior_k": 0.01,
        "binseg_Q": 5,
        "binseg_pen.value": 0,
        "binseg_func": "meanvar",
        "binseg_max_cp": "default",
        "binseg_method": "BinSeg",
        "binseg_penalty": "Hannan-Quinn",
        "binseg_test_statistic": "Normal"
    },
    "args": {
        "bocpd_lambda": 100,
        "bocpd_prior_a": 100,
        "bocpd_prior_b": 100,
        "bocpd_prior_k": 0.01,
        "binseg_func": "meanvar",
        "binseg_max_cp": "default",
        "binseg_method": "BinSeg",
        "binseg_penalty": "Hannan-Quinn",
        "binseg_test_statistic": "Normal"
    },
    "result": {
        "cplocations": [
            16,
            133,
            136,
            140,
            434,
            435,
            884,
            945,
            1002,
            1031,
            1036,
            1140,
            1141,
            1144,
            1150,
            1234,
            1260,
            1599,
            1648,
            1785,
            2020,
            2170,
            2232,
            2456
        ],
        "runtime": 0.893125518
    }
}