{
	"error" : null,
	"command" : "/usr/lib/R/bin/exec/R --slave --no-restore --no-save --slave --file=/TCPDBench/execs/R/cpdbench_changepoint.R --args -i /TCPDBench/datasets/4967483.json -p SIC -f var -t Normal -m BinSeg -Q default",
	"script" : "/TCPDBench/execs/R/cpdbench_changepoint.R",
	"script_md5" : "c5a9eb6b79b918fc674b55b669629f44",
	"hostname" : "7233945ba110",
	"dataset" : "4967483",
	"dataset_md5" : "1f2d3bd59ac9fef1efa2dd5dba83fb18",
	"status" : "SUCCESS",
	"parameters" : {
		"Q" : 5,
		"pen.value" : 0,
		"func" : "var",
		"max_cp" : "default",
		"method" : "BinSeg",
		"penalty" : "SIC",
		"test_statistic" : "Normal"
	},
	"result" : {
		"cplocations" : [
			196,
			228,
			320,
			462,
			891
		],
		"runtime" : 0.004720688
	},
	"args" : {
		"func" : "var",
		"max_cp" : "default",
		"method" : "BinSeg",
		"penalty" : "SIC",
		"test_statistic" : "Normal"
	}
} 
