{
	"error" : null,
	"command" : "/usr/lib/R/bin/exec/R --slave --no-restore --no-save --slave --file=/TCPDBench/execs/R/cpdbench_changepointnp.R --args -i /TCPDBench/datasets/3779889.json -p AIC -q 30",
	"script" : "/TCPDBench/execs/R/cpdbench_changepointnp.R",
	"script_md5" : "43ed9dac8cb9570e29df4eeae78efd13",
	"hostname" : "7233945ba110",
	"dataset" : "3779889",
	"dataset_md5" : "0927fa62315620833e0c0c998b3015d5",
	"status" : "SUCCESS",
	"parameters" : {
		"method" : "PELT",
		"test.stat" : "empirical_distribution",
		"minseglen" : 1,
		"nquantiles" : 30,
		"penalty" : "AIC"
	},
	"result" : {
		"cplocations" : [
			32,
			41,
			50,
			66,
			81,
			98,
			128,
			138,
			148,
			189,
			191,
			213,
			219,
			224,
			230,
			244,
			257,
			263,
			285,
			289,
			306,
			316,
			323,
			341,
			352,
			364,
			405,
			440,
			451,
			459,
			465,
			468,
			475,
			497,
			506,
			518,
			525,
			536,
			549,
			555,
			558,
			571,
			580,
			600,
			614,
			625,
			630,
			634,
			646,
			653,
			660,
			666,
			671,
			676,
			687,
			706,
			708,
			714,
			718,
			725,
			735,
			741,
			749,
			751,
			754,
			756,
			764,
			774,
			783,
			792,
			800,
			804,
			809,
			817,
			821,
			824,
			843,
			851,
			855,
			859,
			897,
			910,
			917,
			922,
			928,
			956,
			979,
			992,
			1044,
			1051,
			1075,
			1100,
			1109,
			1132,
			1163,
			1213,
			1222,
			1237,
			1265,
			1295,
			1323,
			1334,
			1353,
			1363,
			1374,
			1380,
			1442,
			1456,
			1482,
			1492,
			1499,
			1510,
			1518,
			1522,
			1533,
			1543,
			1564,
			1569,
			1621,
			1627,
			1638,
			1664,
			1709,
			1746,
			1751,
			1788,
			1828,
			1897,
			1957,
			1968,
			1975,
			1988,
			2013,
			2045,
			2052,
			2096,
			2130,
			2147,
			2156,
			2172,
			2189,
			2260,
			2307,
			2320,
			2350,
			2357,
			2402,
			2408,
			2416,
			2457,
			2466,
			2480,
			2495,
			2500,
			2548,
			2555,
			2580,
			2589,
			2603,
			2634,
			2644,
			2661,
			2671,
			2683,
			2704,
			2714,
			2743,
			2754,
			2777,
			2794,
			2804,
			2829,
			2858,
			2864,
			2884,
			2888,
			2921,
			2940,
			2947,
			2966,
			2970,
			2975,
			2981,
			2985,
			2988,
			3000,
			3022,
			3051,
			3089,
			3094,
			3103,
			3108,
			3120,
			3135,
			3183,
			3185,
			3193,
			3200,
			3244,
			3248,
			3256,
			3263,
			3278,
			3286,
			3292,
			3302,
			3305,
			3312,
			3338,
			3360,
			3437,
			3465,
			3473,
			3533,
			3540,
			3550,
			3554,
			3562,
			3569,
			3580,
			3586,
			3592,
			3605,
			3607
		],
		"runtime" : 0.04297185
	},
	"args" : {
		"nquantiles" : 30,
		"penalty" : "AIC"
	}
} 
